rmdepcheck.py
rmdepcheck-1.1.0.dist-info/licenses/COPYING
rmdepcheck-1.1.0.dist-info/METADATA
rmdepcheck-1.1.0.dist-info/WHEEL
rmdepcheck-1.1.0.dist-info/entry_points.txt
rmdepcheck-1.1.0.dist-info/top_level.txt
rmdepcheck-1.1.0.dist-info/RECORD
