Metadata-Version: 2.4
Name: rmdepcheck
Version: 1.1.0
Summary: RPM installability and repoclosure checks based on repomd.xml modification
Author-email: Adam Williamson <awilliam@redhat.com>
License-Expression: GPL-3.0-or-later
Project-URL: Homepage, https://codeberg.org/AdamWill/rmdepcheck
Project-URL: Documentation, https://codeberg.org/AdamWill/rmdepcheck/src/branch/main/README.md
Project-URL: Repository, https://codeberg.org/AdamWill/rmdepcheck
Project-URL: Issues, https://codeberg.org/AdamWill/rmdepcheck/issues
Project-URL: Changelog, https://codeberg.org/AdamWill/rmdepcheck/src/branch/main/CHANGELOG.md
Keywords: rpm,dependency,test,check,reverse
Classifier: Development Status :: 5 - Production/Stable
Classifier: Intended Audience :: Developers
Classifier: Operating System :: POSIX :: Linux
Classifier: Programming Language :: Python
Classifier: Programming Language :: Python :: 3.9
Classifier: Programming Language :: Python :: 3.10
Classifier: Programming Language :: Python :: 3.11
Classifier: Programming Language :: Python :: 3.12
Classifier: Programming Language :: Python :: 3.13
Classifier: Programming Language :: Python :: 3.14
Classifier: Topic :: Internet :: WWW/HTTP
Classifier: Topic :: System :: Archiving :: Packaging
Classifier: Topic :: Software Development :: Testing
Requires-Python: >=3.9
License-File: COPYING
Dynamic: license-file
